edges_cal/__init__.py
edges_cal/alanmode.py
edges_cal/cached_property.py
edges_cal/cal_coefficients.py
edges_cal/calobs.py
edges_cal/cli.py
edges_cal/config.py
edges_cal/ee.py
edges_cal/loss.py
edges_cal/noise_waves.py
edges_cal/plot.py
edges_cal/receiver_calibration_func.py
edges_cal/reflection_coefficient.py
edges_cal/s11.py
edges_cal/simulate.py
edges_cal/spectra.py
edges_cal/tools.py
edges_cal/types.py
edges_cal/xrfi.py
edges_cal/data/semi_rigid_s_parameters_2017.txt
edges_cal/data/semi_rigid_s_parameters_WITH_HEADER.txt
edges_cal/modelling/__init__.py
edges_cal/modelling/composite.py
edges_cal/modelling/core.py
edges_cal/modelling/data_transforms.py
edges_cal/modelling/fitting.py
edges_cal/modelling/models.py
edges_cal/modelling/xtransforms.py
edges_cal/notebooks/calibrate-observation.ipynb
edges_cal/notebooks/compare-observation.ipynb
edges_cal-7.1.1.dist-info/licenses/LICENSE.txt
edges_cal-7.1.1.dist-info/METADATA
edges_cal-7.1.1.dist-info/WHEEL
edges_cal-7.1.1.dist-info/entry_points.txt
edges_cal-7.1.1.dist-info/top_level.txt
edges_cal-7.1.1.dist-info/RECORD
