Metadata-Version: 2.4
Name: edges-cal
Version: 7.1.1
Summary: Calibration routines for EDGES data
Author-email: Steven Murray <steven.murray@sns.it>, Nivedita Mahesh <nmahesh4@asu.edu>
License: MIT
Project-URL: Repository, https://github.com/edges-collab/read_caq
Project-URL: Issues, https://github.com/edges-collab/read_acq/issues
Project-URL: Changelog, https://github.com/edges-collab/read_acq/releases
Classifier: Development Status :: 4 - Beta
Classifier: Intended Audience :: Science/Research
Classifier: License :: OSI Approved :: MIT License
Classifier: Operating System :: POSIX
Classifier: Operating System :: Unix
Classifier: Programming Language :: Python
Classifier: Programming Language :: Python :: 3
Classifier: Programming Language :: Python :: 3 :: Only
Classifier: Programming Language :: Python :: Implementation :: CPython
Requires-Python: >=3.10
License-File: LICENSE.txt
Requires-Dist: numpy
Requires-Dist: scipy
Requires-Dist: matplotlib
Requires-Dist: astropy>=5.0
Requires-Dist: edges-io>=4.0
Requires-Dist: toml
Requires-Dist: pyyaml
Requires-Dist: h5py
Requires-Dist: click
Requires-Dist: statsmodels
Requires-Dist: rich
Requires-Dist: hickleable>=0.2.4
Requires-Dist: typing_extensions
Provides-Extra: docs
Requires-Dist: ipython; extra == "docs"
Requires-Dist: nbsphinx; extra == "docs"
Requires-Dist: numpydoc; extra == "docs"
Requires-Dist: sphinx>=4.0; extra == "docs"
Requires-Dist: furo; extra == "docs"
Requires-Dist: myst-parser; extra == "docs"
Requires-Dist: sphinx-click; extra == "docs"
Provides-Extra: report
Requires-Dist: papermill; extra == "report"
Requires-Dist: jupyter; extra == "report"
Requires-Dist: beautifultable; extra == "report"
Provides-Extra: dev
Requires-Dist: edges-cal[docs,report]; extra == "dev"
Requires-Dist: pytest; extra == "dev"
Requires-Dist: pytest-cov; extra == "dev"
Requires-Dist: pytest-cases; extra == "dev"
Requires-Dist: pre-commit; extra == "dev"
Dynamic: license-file
